{"comment":"/**\n * ---\n * category: utilities/react\n * ---\n * Parse the component props for the interaction type. It will return one of 'enabled', 'disabled', or 'readonly'.\n * This is useful for form elements where consumers are able to either use the interaction prop as specified or the\n * native html disabled or readonly attributes\n * @module getInteraction\n * @param {Object} args\n * @param {Object} args.props - the component props\n * @param {string} args.props.interaction - specifies the interaction mode, one of 'enabled', 'disabled', or 'readonly'\n * @param {boolean} args.props.disabled - specifies if the component is disabled. Will take precedence over readOnly\n * @param {boolean} args.props.readOnly - specifies if the component is readonly\n * @param {Array} args.interactionTypes - an array specifying the interaction types available to the component, ['disabled', 'readonly'] by default\n * @returns {String} one of 'enabled', 'disabled', or 'readonly'\n */","meta":{"filename":"iotfzq7o1w9btjbq2jf8b.js","lineno":1,"columnno":0,"path":"/tmp","code":{}},"description":"Parse the component props for the interaction type. It will return one of 'enabled', 'disabled', or 'readonly'.\nThis is useful for form elements where consumers are able to either use the interaction prop as specified or the\nnative html disabled or readonly attributes","kind":"module","name":"getInteraction","params":[{"type":{"names":["Object"]},"name":"args"},{"type":{"names":["Object"]},"description":"the component props","name":"args.props"},{"type":{"names":["string"]},"description":"specifies the interaction mode, one of 'enabled', 'disabled', or 'readonly'","name":"args.props.interaction"},{"type":{"names":["boolean"]},"description":"specifies if the component is disabled. Will take precedence over readOnly","name":"args.props.disabled"},{"type":{"names":["boolean"]},"description":"specifies if the component is readonly","name":"args.props.readOnly"},{"type":{"names":["Array"]},"description":"an array specifying the interaction types available to the component, ['disabled', 'readonly'] by default","name":"args.interactionTypes"}],"returns":[{"type":{"names":["String"]},"description":"one of 'enabled', 'disabled', or 'readonly'"}],"longname":"module:getInteraction","undocumented":false,"category":"utilities/react","relativePath":"packages/ui-react-utils/src/getInteraction.ts","extension":".ts","srcPath":"packages/ui-react-utils/src/getInteraction.ts","srcUrl":"https://github.com/instructure/instructure-ui/tree/master/packages/ui-react-utils/src/getInteraction.ts","packageName":"@instructure/ui-react-utils","requirePath":"@instructure/ui-react-utils/lib/getInteraction","requireStr":"require('/home/runner/work/instructure-ui/instructure-ui/packages/ui-react-utils/src/getInteraction.ts').default","esPath":"@instructure/ui-react-utils/es/getInteraction","themePath":"packages/ui-react-utils/src/getInteraction.ts","themeUrl":"https://github.com/instructure/instructure-ui/tree/master/packages/ui-react-utils/src/getInteraction.ts","id":"getInteraction","title":"getInteraction"}